LICENSE
MANIFEST.in
README.rst
setup.cfg
setup.py
ersciUlmenu/__init__.py
ersciUlmenu/admin.py
ersciUlmenu/apps.py
ersciUlmenu/ersciUlmenu.py
ersciUlmenu/models.py
ersciUlmenu/tests.py
ersciUlmenu/urls.py
ersciUlmenu/views.py
ersciUlmenu/__pycache__/__init__.cpython-310.pyc
ersciUlmenu/__pycache__/admin.cpython-310.pyc
ersciUlmenu/__pycache__/apps.cpython-310.pyc
ersciUlmenu/__pycache__/ersciUlmenu.cpython-310.pyc
ersciUlmenu/__pycache__/models.cpython-310.pyc
ersciUlmenu/migrations/0001_initial.py
ersciUlmenu/migrations/__init__.py
ersciUlmenu/migrations/__pycache__/0001_initial.cpython-310.pyc
ersciUlmenu/migrations/__pycache__/__init__.cpython-310.pyc
ersciUlmenu/template/ersciUlmenutemp/index.html
ersciUlmenu/templatetags/__init__.py
ersciUlmenu/templatetags/ersciUlmenutag.py
ersciUlmenu/templatetags/__pycache__/__init__.cpython-310.pyc
ersciUlmenu/templatetags/__pycache__/ersciUlmenutag.cpython-310.pyc
ersciUlmenu/templatetags/__pycache__/ullimenu.cpython-310.pyc
ersci_ulmenu.egg-info/PKG-INFO
ersci_ulmenu.egg-info/SOURCES.txt
ersci_ulmenu.egg-info/dependency_links.txt
ersci_ulmenu.egg-info/top_level.txt